vk_maria/__init__.py
vk_maria/api.py
vk_maria/dispatcher/__init__.py
vk_maria/dispatcher/dispatcher.py
vk_maria/dispatcher/filters/__init__.py
vk_maria/dispatcher/filters/filters.py
vk_maria/dispatcher/filters/handler.py
vk_maria/dispatcher/fsm/__init__.py
vk_maria/dispatcher/fsm/state.py
vk_maria/dispatcher/fsm/storage/__init__.py
vk_maria/dispatcher/fsm/storage/core.py
vk_maria/dispatcher/fsm/storage/file/__init__.py
vk_maria/dispatcher/fsm/storage/file/base.py
vk_maria/dispatcher/fsm/storage/file/json.py
vk_maria/dispatcher/fsm/storage/file/pickle.py
vk_maria/dispatcher/fsm/storage/memory/__init__.py
vk_maria/dispatcher/fsm/storage/memory/memory.py
vk_maria/exceptions.py
vk_maria/longpoll/__init__.py
vk_maria/longpoll/longpoll.py
vk_maria/mixins.py
vk_maria/responses.py
vk_maria/types/__init__.py
vk_maria/types/callback_query_event.py
vk_maria/types/chat.py
vk_maria/types/event.py
vk_maria/types/event_type.py
vk_maria/types/input_file.py
vk_maria/types/keyboard.py
vk_maria/types/message.py
vk_maria/types/message_event.py
vk_maria/types/state.py
vk_maria/upload/__init__.py
vk_maria/upload/exceptions.py
vk_maria/upload/upload.py
vk_maria/upload/utils.py
vk_maria/utils.py
vk_maria/vk_types.py
vk_maria-3.0.9.dist-info/LICENSE
vk_maria-3.0.9.dist-info/METADATA
vk_maria-3.0.9.dist-info/WHEEL
vk_maria-3.0.9.dist-info/RECORD
