Metadata-Version: 2.3
Name: vk-maria
Version: 3.0.9
Summary: Simple Vk Bot synchronous framework
License: GPL-3.0
Keywords: vk,bot,api,framework,wrapper,sync
Author: lxstvayne
Requires-Python: >=3.8
Classifier: Environment :: Console
Classifier: License :: OSI Approved :: GNU General Public License v3 (GPLv3)
Classifier: Programming Language :: Python :: 3
Classifier: Programming Language :: Python :: 3.8
Classifier: Programming Language :: Python :: 3.9
Classifier: Programming Language :: Python :: 3.10
Classifier: Programming Language :: Python :: 3.11
Classifier: Programming Language :: Python :: 3.12
Classifier: Programming Language :: Python :: 3.13
Classifier: Topic :: Communications :: Chat
Classifier: Topic :: Software Development :: Libraries :: Application Frameworks
Classifier: Topic :: Software Development :: Libraries :: Python Modules
Requires-Dist: loguru (>=0.5.3)
Requires-Dist: pydotdict (>=3.3.11)
Requires-Dist: requests (>=2.20.1)
Project-URL: Documentation, https://vk-maria.readthedocs.io/ru/latest/
Project-URL: Repository, https://github.com/lxstvayne/vk_maria
